P3/Modulos/init.v
module init (
    input  wire        clk,
    input  wire        rst,
    
    // Sinais de controle da SDRAM
    output reg         cke,
    output reg         cs_n,
    output reg         ras_n,
    output reg         cas_n,
    output reg         we_n,
    output reg  [1:0]  ba,
    output reg  [12:0] a,
    
    output reg         ready
);

    // MODOS REGISTRO CORRETO!

    // Quantidade de Auto Refreshs antes do Load Mode Register.
    localparam NUM_AUTOREFRESH = 10;

    // Parâmetros do Mode Register
    // M9 = 1 (Single Location Access)
    // M8:7 = 00 (Standard Operation)
    // M6:4 = 011 (CAS Latency = 3)
    // M3 = 0 (Sequential)
    // M2:0 = 000 (Burst Length = 1)
    // Valor final: 13'b0_0010_0011_0000 = 13'h0230
    localparam MODE_REG = 13'h0230;


    // TEMPOS VALIDADOS (TUDO BEM SER UM POUCO MAIOR!)
    // NÃO PODE SER MAIOR NA LEITURA E ESCRITA (MÁQUINA DE ESTADOS INTERNA)

    // Tempos baseados em 143 MHz (T ~ 7 ns)
    // Espera inicial de 200 us ~ 30000 ciclos (Margem superior)
    localparam TRP  = 4;   // tRP  (20ns)  -> ~3 ciclos, margem 4
    localparam TRC  = 10;  // tRC  (60ns)  -> ~9 ciclos, margem 10
    localparam TMRD = 3;   // tMRD (2 clk) -> margem 3

    // COMANDOS CORRETOS!

    // Comandos SDRAM {cs_n, ras_n, cas_n, we_n}
    localparam CMD_NOP     = 4'b0111;
    localparam CMD_PALL    = 4'b0010;
    localparam CMD_AREF    = 4'b0001;       // Auto Refresh
    localparam CMD_MRS     = 4'b0000;

    // Estados de Inicialização
    localparam S_WAIT     = 3'd0;
    localparam S_PRECH    = 3'd1;
    localparam S_REF1     = 3'd2;
    localparam S_REF2     = 3'd3;
    localparam S_MRS      = 3'd4;
    localparam S_DONE     = 3'd5;

    reg [2:0]  state;
    reg [14:0] timer;
    reg [7:0]  refresh_count;

    always @(posedge clk) begin
        if (rst) begin
            state <= S_WAIT;
            timer <= 15'd0;
            refresh_count <= 8'd0;
            ready <= 1'b0;
            
            cke   <= 1'b1;
            {cs_n, ras_n, cas_n, we_n} <= CMD_NOP;
            ba    <= 2'b00;
            a     <= 13'b0;
        end else begin
            // Decodificação padrão (NOP) se não for enviar comando.
            // Assim, após Precharge e após cada Auto-Refresh, o ciclo seguinte
            // permanece em NOP, como requerido pelo datasheet.
            {cs_n, ras_n, cas_n, we_n} <= CMD_NOP;
            
            case (state)
                S_WAIT: begin
                    timer <= timer + 1'b1;
                    if (timer == 15'd30000) begin
                        state <= S_PRECH;
                        timer <= 15'd0;
                        refresh_count <= 8'd0;
                        
                        // Precharge ALL command
                        {cs_n, ras_n, cas_n, we_n} <= CMD_PALL;
                        a[10] <= 1'b1;
                    end
                end
                
                S_PRECH: begin
                    timer <= timer + 1'b1;
                    if (timer == TRP) begin
                        state <= S_REF1;
                        timer <= 15'd0;
                        refresh_count <= 8'd1;
                        
                        // Auto Refresh 1 command
                        {cs_n, ras_n, cas_n, we_n} <= CMD_AREF;
                    end
                end
                
                S_REF1: begin
                    timer <= timer + 1'b1;
                    if (timer == TRC) begin
                        state <= S_REF2;
                        timer <= 15'd0;
                        refresh_count <= 8'd2;
                        
                        // Auto Refresh 2 command
                        {cs_n, ras_n, cas_n, we_n} <= CMD_AREF;
                    end
                end
                
                S_REF2: begin
                    timer <= timer + 1'b1;
                    if (timer == TRC) begin
                        if (refresh_count >= NUM_AUTOREFRESH) begin
                            state <= S_MRS;
                            timer <= 15'd0;
                            
                            // Load Mode Register command
                            {cs_n, ras_n, cas_n, we_n} <= CMD_MRS;
                            a <= MODE_REG;
                            ba <= 2'b00;
                        end else begin
                            state <= S_REF2;
                            timer <= 15'd0;
                            refresh_count <= refresh_count + 1'b1;
                            
                            // Auto Refresh extra command
                            {cs_n, ras_n, cas_n, we_n} <= CMD_AREF;
                        end
                    end
                end
                
                S_MRS: begin
                    timer <= timer + 1'b1;
                    if (timer == TMRD) begin
                        state <= S_DONE;
                        ready <= 1'b1;
                    end
                end
                
                S_DONE: begin
                    ready <= 1'b1;
                    // NOP command
                    {cs_n, ras_n, cas_n, we_n} <= CMD_NOP;
                end
                
                default: begin
                    state <= S_WAIT;
                    timer <= 15'd0;
                end
            endcase
        end
    end

endmodule

P3/TestBenchs/init_tb.v
`timescale 1ns/1ps

module init_tb;

    // ------------------------------------------------------------
    // Estados e comandos esperados
    // ------------------------------------------------------------

    localparam S_WAIT  = 3'd0;
    localparam S_PRECH = 3'd1;
    localparam S_REF1  = 3'd2;
    localparam S_REF2  = 3'd3;
    localparam S_MRS   = 3'd4;
    localparam S_DONE  = 3'd5;

    localparam CMD_NOP  = 4'b0111;
    localparam CMD_PALL = 4'b0010;
    localparam CMD_AREF = 4'b0001;
    localparam CMD_MRS  = 4'b0000;

    // ------------------------------------------------------------
    // Sinais
    // ------------------------------------------------------------

    reg clk;
    reg rst;

    wire cke;
    wire cs_n;
    wire ras_n;
    wire cas_n;
    wire we_n;
    wire [1:0] ba;
    wire [12:0] a;
    wire ready;

    // ------------------------------------------------------------
    // DUT
    // ------------------------------------------------------------

    init dut (
        .clk(clk),
        .rst(rst),
        .cke(cke),
        .cs_n(cs_n),
        .ras_n(ras_n),
        .cas_n(cas_n),
        .we_n(we_n),
        .ba(ba),
        .a(a),
        .ready(ready)
    );

    // ------------------------------------------------------------
    // Funcoes de nome
    // ------------------------------------------------------------

    function [8*12-1:0] state_name;
        input [2:0] state;
        begin
            case (state)
                S_WAIT:  state_name = "S_WAIT";
                S_PRECH: state_name = "S_PRECH";
                S_REF1:  state_name = "S_REF1";
                S_REF2:  state_name = "S_REF2";
                S_MRS:   state_name = "S_MRS";
                S_DONE:  state_name = "S_DONE";
                default: state_name = "UNKNOWN";
            endcase
        end
    endfunction

    function [8*12-1:0] cmd_name;
        input [3:0] cmd;
        begin
            case (cmd)
                CMD_NOP:  cmd_name = "CMD_NOP";
                CMD_PALL: cmd_name = "CMD_PALL";
                CMD_AREF: cmd_name = "CMD_AREF";
                CMD_MRS:  cmd_name = "CMD_MRS";
                default:   cmd_name = "CMD_INV";
            endcase
        end
    endfunction

    // ------------------------------------------------------------
    // Cobertura visual
    // ------------------------------------------------------------

    integer errors;
    reg seen_wait;
    reg seen_prech;
    reg seen_ref1;
    reg seen_ref2;
    reg seen_mrs;
    reg seen_done;
    reg seen_nop;
    reg seen_pall;
    reg seen_aref;
    reg seen_mrs_cmd;

    reg [2:0] last_state;
    reg [3:0] last_cmd;

    always #5 clk = ~clk;

    always @(posedge clk) begin
        #1;

        if (rst === 1'b0) begin
            if (dut.state !== last_state || {cs_n, ras_n, cas_n, we_n} !== last_cmd) begin
                $display("t=%0t estado=%s comando=%s timer=%0d ready=%b ba=%b a=0x%h",
                         $time,
                         state_name(dut.state),
                         cmd_name({cs_n, ras_n, cas_n, we_n}),
                         dut.timer,
                         ready,
                         ba,
                         a);

                last_state = dut.state;
                last_cmd = {cs_n, ras_n, cas_n, we_n};
            end

            case (dut.state)
                S_WAIT:  seen_wait = 1'b1;
                S_PRECH: seen_prech = 1'b1;
                S_REF1:  seen_ref1 = 1'b1;
                S_REF2:  seen_ref2 = 1'b1;
                S_MRS:   seen_mrs = 1'b1;
                S_DONE:   seen_done = 1'b1;
            endcase

            case ({cs_n, ras_n, cas_n, we_n})
                CMD_NOP:  seen_nop = 1'b1;
                CMD_PALL: seen_pall = 1'b1;
                CMD_AREF: seen_aref = 1'b1;
                CMD_MRS:  seen_mrs_cmd = 1'b1;
            endcase
        end
    end

    // ------------------------------------------------------------
    // Estimulo principal
    // ------------------------------------------------------------

    initial begin
        clk = 1'b0;
        rst = 1'b1;

        errors = 0;
        seen_wait = 1'b0;
        seen_prech = 1'b0;
        seen_ref1 = 1'b0;
        seen_ref2 = 1'b0;
        seen_mrs = 1'b0;
        seen_done = 1'b0;
        seen_nop = 1'b0;
        seen_pall = 1'b0;
        seen_aref = 1'b0;
        seen_mrs_cmd = 1'b0;
        last_state = 3'bxxx;
        last_cmd = 4'bxxxx;

        $dumpfile("init_tb.vcd");
        $dumpvars(0, init_tb);

        $display("========================================");
        $display("TB INIT - VISUALIZACAO DE ESTADOS E COMANDOS");

        repeat (2) @(posedge clk);
        #1;

        if (dut.state !== S_WAIT) begin
            $display("[ERRO] Estado inicial esperado S_WAIT, mas foi %0d", dut.state);
            errors = errors + 1;
        end

        rst = 1'b0;
        $display("Reset liberado. Aguardando sequencia completa da inicializacao.");

        wait (ready === 1'b1);
        #1;

        if (!seen_wait) begin
            $display("[ERRO] S_WAIT nao foi observado");
            errors = errors + 1;
        end

        if (!seen_prech) begin
            $display("[ERRO] S_PRECH nao foi observado");
            errors = errors + 1;
        end

        if (!seen_ref1) begin
            $display("[ERRO] S_REF1 nao foi observado");
            errors = errors + 1;
        end

        if (!seen_ref2) begin
            $display("[ERRO] S_REF2 nao foi observado");
            errors = errors + 1;
        end

        if (!seen_mrs) begin
            $display("[ERRO] S_MRS nao foi observado");
            errors = errors + 1;
        end

        if (!seen_done) begin
            $display("[ERRO] S_DONE nao foi observado");
            errors = errors + 1;
        end

        if (!seen_nop) begin
            $display("[ERRO] CMD_NOP nao foi observado");
            errors = errors + 1;
        end

        if (!seen_pall) begin
            $display("[ERRO] CMD_PALL nao foi observado");
            errors = errors + 1;
        end

        if (!seen_aref) begin
            $display("[ERRO] CMD_AREF nao foi observado");
            errors = errors + 1;
        end

        if (!seen_mrs_cmd) begin
            $display("[ERRO] CMD_MRS nao foi observado");
            errors = errors + 1;
        end

        if (a !== 13'h0230) begin
            $display("[ERRO] MODE REGISTER incorreto: a=0x%h", a);
            errors = errors + 1;
        end

        $display("----------------------------------------");
        $display("Resumo da inicializacao:");
        $display("state=%s command=%s ready=%b", state_name(dut.state), cmd_name({cs_n, ras_n, cas_n, we_n}), ready);

        if (errors == 0)
            $display("RESULTADO: init validada com visualizacao completa dos estados e comandos");
        else
            $display("RESULTADO: %0d erro(s) encontrados", errors);

        $display("========================================");

        #20;
        $finish;
    end

endmodule

P3/QuartusProjetoV2/simulation/modelsim/init_tb.vcd
$date
	Wed Jun 17 17:02:21 2026
$end
$version
	ModelSim Version 10.5b
$end
$timescale
	1ps
$end

$scope module init_tb $end
$var parameter 3 ! S_WAIT $end
$var parameter 3 " S_PRECH $end
$var parameter 3 # S_REF1 $end
$var parameter 3 $ S_REF2 $end
$var parameter 3 % S_MRS $end
$var parameter 3 & S_DONE $end
$var parameter 4 ' CMD_NOP $end
$var parameter 4 ( CMD_PALL $end
$var parameter 4 ) CMD_AREF $end
$var parameter 4 * CMD_MRS $end
$var reg 1 + clk $end
$var reg 1 , rst $end
$var wire 1 - cke $end
$var wire 1 . cs_n $end
$var wire 1 / ras_n $end
$var wire 1 0 cas_n $end
$var wire 1 1 we_n $end
$var wire 1 2 ba [1] $end
$var wire 1 3 ba [0] $end
$var wire 1 4 a [12] $end
$var wire 1 5 a [11] $end
$var wire 1 6 a [10] $end
$var wire 1 7 a [9] $end
$var wire 1 8 a [8] $end
$var wire 1 9 a [7] $end
$var wire 1 : a [6] $end
$var wire 1 ; a [5] $end
$var wire 1 < a [4] $end
$var wire 1 = a [3] $end
$var wire 1 > a [2] $end
$var wire 1 ? a [1] $end
$var wire 1 @ a [0] $end
$var wire 1 A ready $end
$var integer 32 B errors $end
$var reg 1 C seen_wait $end
$var reg 1 D seen_prech $end
$var reg 1 E seen_ref1 $end
$var reg 1 F seen_ref2 $end
$var reg 1 G seen_mrs $end
$var reg 1 H seen_done $end
$var reg 1 I seen_nop $end
$var reg 1 J seen_pall $end
$var reg 1 K seen_aref $end
$var reg 1 L seen_mrs_cmd $end
$var reg 3 M last_state [2:0] $end
$var reg 4 N last_cmd [3:0] $end

$scope function state_name $end
$var reg 96 O state_name [95:0] $end
$var reg 3 P state [2:0] $end
$upscope $end

$scope function cmd_name $end
$var reg 96 Q cmd_name [95:0] $end
$var reg 4 R cmd [3:0] $end
$upscope $end

$scope module dut $end
$var parameter 32 S NUM_AUTOREFRESH $end
$var parameter 13 T MODE_REG $end
$var parameter 32 U TRP $end
$var parameter 32 V TRC $end
$var parameter 32 W TMRD $end
$var parameter 4 X CMD_NOP $end
$var parameter 4 Y CMD_PALL $end
$var parameter 4 Z CMD_AREF $end
$var parameter 4 [ CMD_MRS $end
$var parameter 3 \ S_WAIT $end
$var parameter 3 ] S_PRECH $end
$var parameter 3 ^ S_REF1 $end
$var parameter 3 _ S_REF2 $end
$var parameter 3 ` S_MRS $end
$var parameter 3 a S_DONE $end
$var wire 1 b clk $end
$var wire 1 c rst $end
$var reg 1 d cke $end
$var reg 1 e cs_n $end
$var reg 1 f ras_n $end
$var reg 1 g cas_n $end
$var reg 1 h we_n $end
$var reg 2 i ba [1:0] $end
$var reg 13 j a [12:0] $end
$var reg 1 k ready $end
$var reg 3 l state [2:0] $end
$var reg 15 m timer [14:0] $end
$var reg 8 n refresh_count [7:0] $end
$upscope $end
$upscope $end
$enddefinitions $end
#0
$dumpvars
0+
1,
xd
xe
xf
xg
xh
bx i
bx j
xk
bx l
bx m
bx n
bx O
bx P
bx Q
bx R
0C
0D
0E
0F
0G
0H
0I
0J
0K
0L
bx M
bx N
b0 !
b1 "
b10 #
b11 $
b100 %
b101 &
b111 '
b10 (
b1 )
b0 *
b1010 S
b1000110000 T
b100 U
b1010 V
b11 W
b111 X
b10 Y
b1 Z
b0 [
b0 \
b1 ]
b10 ^
b11 _
b100 `
b101 a
b0 B
x-
x.
x/
x0
x1
x3
x2
x@
x?
x>
x=
x<
x;
x:
x9
x8
x7
x6
x5
x4
xA
1c
0b
$end
#5000
1+
1b
b0 l
b0 m
b0 n
0k
1d
1h
1g
1f
0e
b0 i
b0 j
0A
1-
11
10
1/
0.
0@
0?
0>
0=
0<
0;
0:
09
08
07
06
05
04
03
02
#10000
0+
0b
#15000
1+
1b
#16000
0,
0c
#20000
0+
0b
#25000
1+
1b
b1 m
#26000
b0 P
b10100110101111101010111010000010100100101010100 O
b111 R
b1000011010011010100010001011111010011100100111101010000 Q
b0 M
b111 N
1C
1I
#30000
0+
0b
#35000
1+
1b
b10 m
#40000
0+
0b
#45000
1+
1b
b11 m
#50000
0+
0b
#55000
1+
1b
b100 m
#60000
0+
0b
#65000
1+
1b
b101 m
#70000
0+
0b
#75000
1+
1b
b110 m
#80000
0+
0b
#85000
1+
1b
b111 m
#90000
0+
0b
#95000
1+
1b
b1000 m
#100000
0+
0b
#105000
1+
1b
b1001 m
#110000
0+
0b
#115000
1+
1b
b1010 m
#120000
0+
0b
#125000
1+
1b
b1011 m
#130000
0+
0b
#135000
1+
1b
b1100 m
#140000
0+
0b
#145000
1+
1b
b1101 m
#150000
0+
0b
#155000
1+
1b
b1110 m
#160000
0+
0b
#165000
1+
1b
b1111 m
#170000
0+
0b
#175000
1+
1b
b10000 m
#180000
0+
0b
#185000
1+
1b
b10001 m
#190000
0+
0b
#195000
1+
1b
b10010 m
#200000
0+
0b
#205000
1+
1b
b10011 m
#210000
0+
0b
#215000
1+
1b
b10100 m
#220000
0+
0b
#225000
1+
1b
b10101 m
#230000
0+
0b
#235000
1+
1b
b10110 m
#240000
0+
0b
#245000
1+
1b
b10111 m
#250000
0+
0b
#255000
1+
1b
b11000 m
#260000
0+
0b
#265000
1+
1b
b11001 m
#270000
0+
0b
#275000
1+
1b
b11010 m
#280000
0+
0b
#285000
1+
1b
b11011 m
#290000
0+
0b
#295000
1+
1b
b11100 m
#300000
0+
0b
#305000
1+
1b
b11101 m
#310000
0+
0b
#315000
1+
1b
b11110 m
#320000
0+
0b
#325000
1+
1b
b11111 m
#330000
0+
0b
#335000
1+
1b
b100000 m
#340000
0+
0b
#345000
1+
1b
b100001 m
#350000
0+
0b
#355000
1+
1b
b100010 m
#360000
0+
0b
#365000
1+
1b
b100011 m
#370000
0+
0b
#375000
1+
1b
b100100 m
#380000
0+
0b
#385000
1+
1b
b100101 m
#390000
0+
0b
#395000
1+
1b
b100110 m
#400000
0+
0b
#405000
1+
1b
b100111 m
#410000
0+
0b
#415000
1+
1b
b101000 m
#420000
0+
0b
#425000
1+
1b
b101001 m
#430000
0+
0b
#435000
1+
1b
b101010 m
#440000
0+
0b
#445000
1+
1b
b101011 m
#450000
0+
0b
#455000
1+
1b
b101100 m
#460000
0+
0b
#465000
1+
1b
b101101 m
#470000
0+
0b
#475000
1+
1b
b101110 m
#480000
0+
0b
#485000
1+
1b
b101111 m
#490000
0+
0b
#495000
1+
1b
b110000 m
#500000
0+
0b
#505000
1+
1b
b110001 m
#510000
0+
0b
#515000
1+
1b
b110010 m
#520000
0+
0b
#525000
1+
1b
b110011 m
#530000
0+
0b
#535000
1+
1b
b110100 m
#540000
0+
0b
#545000
1+
1b
b110101 m
#550000
0+
0b
#555000
1+
1b
b110110 m
#560000
0+
0b
#565000
1+
1b
b110111 m
#570000
0+
0b
#575000
1+
1b
b111000 m
#580000
0+
0b
#585000
1+
1b
b111001 m
#590000
0+
0b
#595000
1+
1b
b111010 m
#600000
0+
0b
#605000
1+
1b
b111011 m
#610000
0+
0b
#615000
1+
1b
b111100 m
#620000
0+
0b
#625000
1+
1b
b111101 m
#630000
0+
0b
#635000
1+
1b
b111110 m
#640000
0+
0b
#645000
1+
1b
b111111 m
#650000
0+
0b
#655000
1+
1b
b1000000 m
#660000
0+
0b
#665000
1+
1b
b1000001 m
#670000
0+
0b
#675000
1+
1b
b1000010 m
#680000
0+
0b
#685000
1+
1b
b1000011 m
#690000
0+
0b
#695000
1+
1b
b1000100 m
#700000
0+
0b
#705000
1+
1b
b1000101 m
#710000
0+
0b
#715000
1+
1b
b1000110 m
#720000
0+
0b
#725000
1+
1b
b1000111 m
#730000
0+
0b
#735000
1+
1b
b1001000 m
#740000
0+
0b
#745000
1+
1b
b1001001 m
#750000
0+
0b
#755000
1+
1b
b1001010 m
#760000
0+
0b
#765000
1+
1b
b1001011 m
#770000
0+
0b
#775000
1+
1b
b1001100 m
#780000
0+
0b
#785000
1+
1b
b1001101 m
#790000
0+
0b
#795000
1+
1b
b1001110 m
#800000
0+
0b
#805000
1+
1b
b1001111 m
#810000
0+
0b
#815000
1+
1b
b1010000 m
#820000
0+
0b
#825000
1+
1b
b1010001 m
#830000
0+
0b
#835000
1+
1b
b1010010 m
#840000
0+
0b
#845000
1+
1b
b1010011 m
#850000
0+
0b
#855000
1+
1b
b1010100 m
#860000
0+
0b
#865000
1+
1b
b1010101 m
#870000
0+
0b
#875000
1+
1b
b1010110 m
#880000
0+
0b
#885000
1+
1b
b1010111 m
#890000
0+
0b
#895000
1+
1b
b1011000 m
#900000
0+
0b
#905000
1+
1b
b1011001 m
#910000
0+
0b
#915000
1+
1b
b1011010 m
#920000
0+
0b
#925000
1+
1b
b1011011 m
#930000
0+
0b
#935000
1+
1b
b1011100 m
#940000
0+
0b
#945000
1+
1b
b1011101 m
#950000
0+
0b
#955000
1+
1b
b1011110 m
#960000
0+
0b
#965000
1+
1b
b1011111 m
#970000
0+
0b
#975000
1+
1b
b1100000 m
#980000
0+
0b
#985000
1+
1b
b1100001 m
#990000
0+
0b
#995000
1+
1b
b1100010 m
#1000000
0+
0b
#1005000
1+
1b
b1100011 m
#1010000
0+
0b
#1015000
1+
1b
b1100100 m
#1020000
0+
0b
#1025000
1+
1b
b1100101 m
#1030000
0+
0b
#1035000
1+
1b
b1100110 m
#1040000
0+
0b
#1045000
1+
1b
b1100111 m
#1050000
0+
0b
#1055000
1+
1b
b1101000 m
#1060000
0+
0b
#1065000
1+
1b
b1101001 m
#1070000
0+
0b
#1075000
1+
1b
b1101010 m
#1080000
0+
0b
#1085000
1+
1b
b1101011 m
#1090000
0+
0b
#1095000
1+
1b
b1101100 m
#1100000
0+
0b
#1105000
1+
1b
b1101101 m
#1110000
0+
0b
#1115000
1+
1b
b1101110 m
#1120000
0+
0b
#1125000
1+
1b
b1101111 m
#1130000
0+
0b
#1135000
1+
1b
b1110000 m
#1140000
0+
0b
#1145000
1+
1b
b1110001 m
#1150000
0+
0b
#1155000
1+
1b
b1110010 m
#1160000
0+
0b
#1165000
1+
1b
b1110011 m
#1170000
0+
0b
#1175000
1+
1b
b1110100 m
#1180000
0+
0b
#1185000
1+
1b
b1110101 m
#1190000
0+
0b
#1195000
1+
1b
b1110110 m
#1200000
0+
0b
#1205000
1+
1b
b1110111 m
#1210000
0+
0b
#1215000
1+
1b
b1111000 m
#1220000
0+
0b
#1225000
1+
1b
b1111001 m
#1230000
0+
0b
#1235000
1+
1b
b1111010 m
#1240000
0+
0b
#1245000
1+
1b
b1111011 m
#1250000
0+
0b
#1255000
1+
1b
b1111100 m
#1260000
0+
0b
#1265000
1+
1b
b1111101 m
#1270000
0+
0b
#1275000
1+
1b
b1111110 m
#1280000
0+
0b
#1285000
1+
1b
b1111111 m
#1290000
0+
0b
#1295000
1+
1b
b10000000 m
#1300000
0+
0b
#1305000
1+
1b
b10000001 m
#1310000
0+
0b
#1315000
1+
1b
b10000010 m
#1320000
0+
0b
#1325000
1+
1b
b10000011 m
#1330000
0+
0b
#1335000
1+
1b
b10000100 m
#1340000
0+
0b
#1345000
1+
1b
b10000101 m
#1350000
0+
0b
#1355000
1+
1b
b10000110 m
#1360000
0+
0b
#1365000
1+
1b
b10000111 m
#1370000
0+
0b
#1375000
1+
1b
b10001000 m
#1380000
0+
0b
#1385000
1+
1b
b10001001 m
#1390000
0+
0b
#1395000
1+
1b
b10001010 m
#1400000
0+
0b
#1405000
1+
1b
b10001011 m
#1410000
0+
0b
#1415000
1+
1b
b10001100 m
#1420000
0+
0b
#1425000
1+
1b
b10001101 m
#1430000
0+
0b
#1435000
1+
1b
b10001110 m
#1440000
0+
0b
#1445000
1+
1b
b10001111 m
#1450000
0+
0b
#1455000
1+
1b
b10010000 m
#1460000
0+
0b
#1465000
1+
1b
b10010001 m
#1470000
0+
0b
#1475000
1+
1b
b10010010 m
#1480000
0+
0b
#1485000
1+
1b
b10010011 m
#1490000
0+
0b
#1495000
1+
1b
b10010100 m
#1500000
0+
0b
#1505000
1+
1b
b10010101 m
#1510000
0+
0b
#1515000
1+
1b
b10010110 m
#1520000
0+
0b
#1525000
1+
1b
b10010111 m
#1530000
0+
0b
#1535000
1+
1b
b10011000 m
#1540000
0+
0b
#1545000
1+
1b
b10011001 m
#1550000
0+
0b
#1555000
1+
1b
b10011010 m
#1560000
0+
0b
#1565000
1+
1b
b10011011 m
#1570000
0+
0b
#1575000
1+
1b
b10011100 m
#1580000
0+
0b
#1585000
1+
1b
b10011101 m
#1590000
0+
0b
#1595000
1+
1b
b10011110 m
#1600000
0+
0b
#1605000
1+
1b
b10011111 m
#1610000
0+
0b
#1615000
1+
1b
b10100000 m
#1620000
0+
0b
#1625000
1+
1b
b10100001 m
#1630000
0+
0b
#1635000
1+
1b
b10100010 m
#1640000
0+
0b
#1645000
1+
1b
b10100011 m
#1650000
0+
0b
#1655000
1+
1b
b10100100 m
#1660000
0+
0b
#1665000
1+
1b
b10100101 m
#1670000
0+
0b
#1675000
1+
1b
b10100110 m
#1680000
0+
0b
#1685000
1+
1b
b10100111 m
#1690000
0+
0b
#1695000
1+
1b
b10101000 m
#1700000
0+
0b
#1705000
1+
1b
b10101001 m
#1710000
0+
0b
#1715000
1+
1b
b10101010 m
#1720000
0+
0b
#1725000
1+
1b
b10101011 m
#1730000
0+
0b
#1735000
1+
1b
b10101100 m
#1740000
0+
0b
#1745000
1+
1b
b10101101 m
#1750000
0+
0b
#1755000
1+
1b
b10101110 m
#1760000
0+
0b
#1765000
1+
1b
b10101111 m
#1770000
0+
0b
#1775000
1+
1b
b10110000 m
#1780000
0+
0b
#1785000
1+
1b
b10110001 m
#1790000
0+
0b
#1795000
1+
1b
b10110010 m
#1800000
0+
0b
#1805000
1+
1b
b10110011 m
#1810000
0+
0b
#1815000
1+
1b
b10110100 m
#1820000
0+
0b
#1825000
1+
1b
b10110101 m
#1830000
0+
0b
#1835000
1+
1b
b10110110 m
#1840000
0+
0b
#1845000
1+
1b
b10110111 m
#1850000
0+
0b
#1855000
1+
1b
b10111000 m
#1860000
0+
0b
#1865000
1+
1b
b10111001 m
#1870000
0+
0b
#1875000
1+
1b
b10111010 m
#1880000
0+
0b
#1885000
1+
1b
b10111011 m
#1890000
0+
0b
#1895000
1+
1b
b10111100 m
#1900000
0+
0b
#1905000
1+
1b
b10111101 m
#1910000
0+
0b
#1915000
1+
1b
b10111110 m
#1920000
0+
0b
#1925000
1+
1b
b10111111 m
#1930000
0+
0b
#1935000
1+
1b
b11000000 m
#1940000
0+
0b
#1945000
1+
1b
b11000001 m
#1950000
0+
0b
#1955000
1+
1b
b11000010 m
#1960000
0+
0b
#1965000
1+
1b
b11000011 m
#1970000
0+
0b
#1975000
1+
1b
b11000100 m
#1980000
0+
0b
#1985000
1+
1b
b11000101 m
#1990000
0+
0b
#1995000
1+
1b
b11000110 m
#2000000
0+
0b
#2005000
1+
1b
b11000111 m
#2010000
0+
0b
#2015000
1+
1b
b11001000 m
#2020000
0+
0b
#2025000
1+
1b
b11001001 m
#2030000
0+
0b
#2035000
1+
1b
b11001010 m
#2040000
0+
0b
#2045000
1+
1b
b11001011 m
#2050000
0+
0b
#2055000
1+
1b
b11001100 m
#2060000
0+
0b
#2065000
1+
1b
b11001101 m
#2070000
0+
0b
#2075000
1+
1b
b11001110 m
#2080000
0+
0b
#2085000
1+
1b
b11001111 m
#2090000
0+
0b
#2095000
1+
1b
b11010000 m
#2100000
0+
0b
#2105000
1+
1b
b11010001 m
#2110000
0+
0b
#2115000
1+
1b
b11010010 m
#2120000
0+
0b
#2125000
1+
1b
b11010011 m
#2130000
0+
0b
#2135000
1+
1b
b11010100 m
#2140000
0+
0b
#2145000
1+
1b
b11010101 m
#2150000
0+
0b
#2155000
1+
1b
b11010110 m
#2160000
0+
0b
#2165000
1+
1b
b11010111 m
#2170000
0+
0b
#2175000
1+
1b
b11011000 m
#2180000
0+
0b
#2185000
1+
1b
b11011001 m
#2190000
0+
0b
#2195000
1+
1b
b11011010 m
#2200000
0+
0b
#2205000
1+
1b
b11011011 m
#2210000
0+
0b
#2215000
1+
1b
b11011100 m
#2220000
0+
0b
#2225000
1+
1b
b11011101 m
#2230000
0+
0b
#2235000
1+
1b
b11011110 m
#2240000
0+
0b
#2245000
1+
1b
b11011111 m
#2250000
0+
0b
#2255000
1+
1b
b11100000 m
#2260000
0+
0b
#2265000
1+
1b
b11100001 m
#2270000
0+
0b
#2275000
1+
1b
b11100010 m
#2280000
0+
0b
#2285000
1+
1b
b11100011 m
#2290000
0+
0b
#2295000
1+
1b
b11100100 m
#2300000
0+
0b
#2305000
1+
1b
b11100101 m
#2310000
0+
0b
#2315000
1+
1b
b11100110 m
#2320000
0+
0b
#2325000
1+
1b
b11100111 m
#2330000
0+
0b
#2335000
1+
1b
b11101000 m
#2340000
0+
0b
#2345000
1+
1b
b11101001 m
#2350000
0+
0b
#2355000
1+
1b
b11101010 m
#2360000
0+
0b
#2365000
1+
1b
b11101011 m
#2370000
0+
0b
#2375000
1+
1b
b11101100 m
#2380000
0+
0b
#2385000
1+
1b
b11101101 m
#2390000
0+
0b
#2395000
1+
1b
b11101110 m
#2400000
0+
0b
#2405000
1+
1b
b11101111 m
#2410000
0+
0b
#2415000
1+
1b
b11110000 m
#2420000
0+
0b
#2425000
1+
1b
b11110001 m
#2430000
0+
0b
#2435000
1+
1b
b11110010 m
#2440000
0+
0b
#2445000
1+
1b
b11110011 m
#2450000
0+
0b
#2455000
1+
1b
b11110100 m
#2460000
0+
0b
#2465000
1+
1b
b11110101 m
#2470000
0+
0b
#2475000
1+
1b
b11110110 m
#2480000
0+
0b
#2485000
1+
1b
b11110111 m
#2490000
0+
0b
#2495000
1+
1b
b11111000 m
#2500000
0+
0b
#2505000
1+
1b
b11111001 m
#2510000
0+
0b
#2515000
1+
1b
b11111010 m
#2520000
0+
0b
#2525000
1+
1b
b11111011 m
#2530000
0+
0b
#2535000
1+
1b
b11111100 m
#2540000
0+
0b
#2545000
1+
1b
b11111101 m
#2550000
0+
0b
#2555000
1+
1b
b11111110 m
#2560000
0+
0b
#2565000
1+
1b
b11111111 m
#2570000
0+
0b
#2575000
1+
1b
b100000000 m
#2580000
0+
0b
#2585000
1+
1b
b100000001 m
#2590000
0+
0b
#2595000
1+
1b
b100000010 m
#2600000
0+
0b
#2605000
1+
1b
b100000011 m
#2610000
0+
0b
#2615000
1+
1b
b100000100 m
#2620000
0+
0b
#2625000
1+
1b
b100000101 m
#2630000
0+
0b
#2635000
1+
1b
b100000110 m
#2640000
0+
0b
#2645000
1+
1b
b100000111 m
#2650000
0+
0b
#2655000
1+
1b
b100001000 m
#2660000
0+
0b
#2665000
1+
1b
b100001001 m
#2670000
0+
0b
#2675000
1+
1b
b100001010 m
#2680000
0+
0b
#2685000
1+
1b
b100001011 m
#2690000
0+
0b
#2695000
1+
1b
b100001100 m
#2700000
0+
0b
#2705000
1+
1b
b100001101 m
#2710000
0+
0b
#2715000
1+
1b
b100001110 m
#2720000
0+
0b
#2725000
1+
1b
b100001111 m
#2730000
0+
0b
#2735000
1+
1b
b100010000 m
#2740000
0+
0b
#2745000
1+
1b
b100010001 m
#2750000
0+
0b
#2755000
1+
1b
b100010010 m
#2760000
0+
0b
#2765000
1+
1b
b100010011 m
#2770000
0+
0b
#2775000
1+
1b
b100010100 m
#2780000
0+
0b
#2785000
1+
1b
b100010101 m
#2790000
0+
0b
#2795000
1+
1b
b100010110 m
#2800000
0+
0b
#2805000
1+
1b
b100010111 m
#2810000
0+
0b
#2815000
1+
1b
b100011000 m
#2820000
0+
0b
#2825000
1+
1b
b100011001 m
#2830000
0+
0b
#2835000
1+
1b
b100011010 m
#2840000
0+
0b
#2845000
1+
1b
b100011011 m
